graph/__init__.py
graph/react.py
migrations/models/0_20240718114626_init.py
pyagenity_api/__init__.py
pyagenity_api/cli.py
pyagenity_api/src/__init__.py
pyagenity_api/src/app/__init__.py
pyagenity_api/src/app/loader.py
pyagenity_api/src/app/main.py
pyagenity_api/src/app/worker.py
pyagenity_api/src/app/core/__init__.py
pyagenity_api/src/app/core/auth/__init__.py
pyagenity_api/src/app/core/auth/auth_backend.py
pyagenity_api/src/app/core/auth/authentication.py
pyagenity_api/src/app/core/config/__init__.py
pyagenity_api/src/app/core/config/graph_config.py
pyagenity_api/src/app/core/config/sentry_config.py
pyagenity_api/src/app/core/config/settings.py
pyagenity_api/src/app/core/config/setup_logs.py
pyagenity_api/src/app/core/config/setup_middleware.py
pyagenity_api/src/app/core/config/worker_middleware.py
pyagenity_api/src/app/core/exceptions/__init__.py
pyagenity_api/src/app/core/exceptions/general_exception.py
pyagenity_api/src/app/core/exceptions/handle_errors.py
pyagenity_api/src/app/core/exceptions/resources_exceptions.py
pyagenity_api/src/app/core/exceptions/user_exception.py
pyagenity_api/src/app/routers/__init__.py
pyagenity_api/src/app/routers/setup_router.py
pyagenity_api/src/app/routers/checkpointer/__init__.py
pyagenity_api/src/app/routers/checkpointer/router.py
pyagenity_api/src/app/routers/checkpointer/schemas/__init__.py
pyagenity_api/src/app/routers/checkpointer/schemas/checkpointer_schemas.py
pyagenity_api/src/app/routers/checkpointer/services/__init__.py
pyagenity_api/src/app/routers/checkpointer/services/checkpointer_service.py
pyagenity_api/src/app/routers/graph/__init__.py
pyagenity_api/src/app/routers/graph/router.py
pyagenity_api/src/app/routers/graph/schemas/__init__.py
pyagenity_api/src/app/routers/graph/schemas/graph_schemas.py
pyagenity_api/src/app/routers/graph/services/__init__.py
pyagenity_api/src/app/routers/graph/services/dummy_name_generator.py
pyagenity_api/src/app/routers/graph/services/graph_service.py
pyagenity_api-1.0.0.dist-info/METADATA
pyagenity_api-1.0.0.dist-info/WHEEL
pyagenity_api-1.0.0.dist-info/entry_points.txt
pyagenity_api-1.0.0.dist-info/top_level.txt
pyagenity_api-1.0.0.dist-info/RECORD
