Metadata-Version: 2.4
Name: pyagenity-api
Version: 1.0.0
Summary: A Python API framework with GraphQL support and task management
Author-email: Shudipto Trafder <iamsdt@duck.com>
Maintainer-email: Shudipto Trafder <iamsdt@duck.com>
License: MIT
Project-URL: Homepage, https://github.com/Iamsdt/pyagenity-api
Project-URL: Repository, https://github.com/Iamsdt/pyagenity-api
Project-URL: Issues, https://github.com/Iamsdt/pyagenity-api/issues
Project-URL: Documentation, https://pyagenity-api.readthedocs.io/
Keywords: api,fastapi,graphql,task-management,cli
Classifier: Development Status :: 4 - Beta
Classifier: Intended Audience :: Developers
Classifier: License :: OSI Approved :: MIT License
Classifier: Operating System :: OS Independent
Classifier: Programming Language :: Python :: 3
Classifier: Programming Language :: Python :: 3.9
Classifier: Programming Language :: Python :: 3.10
Classifier: Programming Language :: Python :: 3.11
Classifier: Programming Language :: Python :: 3.12
Classifier: Programming Language :: Python :: 3.13
Classifier: Topic :: Software Development :: Libraries :: Python Modules
Classifier: Topic :: Internet :: WWW/HTTP :: HTTP Servers
Classifier: Framework :: FastAPI
Requires-Python: >=3.9
Requires-Dist: aerich==0.7.2
Requires-Dist: aiosmtplib==2.0.2
Requires-Dist: aiofiles==24.1.0
Requires-Dist: asyncpg
Requires-Dist: fastapi
Requires-Dist: firebase-admin==6.5.0
Requires-Dist: gunicorn==23.0.0
Requires-Dist: httpx==0.27.0
Requires-Dist: injector==0.22.0
Requires-Dist: lib==4.0.0
Requires-Dist: markdown-it-py==3.0.0
Requires-Dist: mkdocs-gen-files==0.5.0
Requires-Dist: mkdocstrings==0.25.2
Requires-Dist: mypy-extensions==1.0.0
Requires-Dist: oauth2client==4.1.3
Requires-Dist: orjson
Requires-Dist: pre-commit==3.8.0
Requires-Dist: python-multipart==0.0.19
Requires-Dist: pydantic==2.8.2
Requires-Dist: pydantic-settings==2.3.4
Requires-Dist: pytest==8.3.2
Requires-Dist: pytest-env==1.1.3
Requires-Dist: redis==5.0.7
Requires-Dist: requests==2.32.3
Requires-Dist: ruff==0.5.2
Requires-Dist: sentry-sdk==2.10.0
Requires-Dist: snowflakekit
Requires-Dist: starlette==0.40.0
Requires-Dist: strawberry-graphql==0.257.0
Requires-Dist: taskiq==0.11.10
Requires-Dist: taskiq-redis==1.0.0
Requires-Dist: tortoise==0.1.1
Requires-Dist: tortoise-orm==0.22.1
Requires-Dist: uvicorn==0.30.1
Requires-Dist: typer
Requires-Dist: python-dotenv
